odoo/addons/hr_announcement/README.rst
odoo/addons/hr_announcement/__init__.py
odoo/addons/hr_announcement/__manifest__.py
odoo/addons/hr_announcement/i18n/es.po
odoo/addons/hr_announcement/i18n/hr_announcement.pot
odoo/addons/hr_announcement/i18n/it.po
odoo/addons/hr_announcement/models/__init__.py
odoo/addons/hr_announcement/models/announcement.py
odoo/addons/hr_announcement/models/res_users.py
odoo/addons/hr_announcement/readme/CONTRIBUTORS.md
odoo/addons/hr_announcement/readme/DESCRIPTION.md
odoo/addons/hr_announcement/readme/USAGE.md
odoo/addons/hr_announcement/static/description/icon.png
odoo/addons/hr_announcement/static/description/index.html
odoo/addons/hr_announcement/views/announcement_views.xml
odoo_addon_hr_announcement-17.0.1.0.0.2.dist-info/METADATA
odoo_addon_hr_announcement-17.0.1.0.0.2.dist-info/WHEEL
odoo_addon_hr_announcement-17.0.1.0.0.2.dist-info/top_level.txt
odoo_addon_hr_announcement-17.0.1.0.0.2.dist-info/RECORD
